synthesizrr/__init__.py
synthesizrr/common.py
synthesizrr/corpus.py
synthesizrr/data.py
synthesizrr/driver.py
synthesizrr/generation.py
synthesizrr/main.py
synthesizrr/metrics.py
synthesizrr-0.1.0.dist-info/METADATA
synthesizrr-0.1.0.dist-info/WHEEL
synthesizrr-0.1.0.dist-info/licenses/LICENSE
synthesizrr-0.1.0.dist-info/RECORD
