Metadata-Version: 2.4
Name: synthesizrr
Version: 0.1.0
Summary: Synthesizing realistic and diverse text-datasets from augmented LLMs.
Author-email: Abhishek Divekar <adivekar@utexas.edu>
License-File: LICENSE
Classifier: Operating System :: OS Independent
Classifier: Programming Language :: Python :: 3
Requires-Python: >=3.11
Requires-Dist: fmcore[all]
